golem/__init__.py
golem/__main__.py
golem/cli/__init__.py
golem/cli/cli.py
golem/cli/utils.py
golem/event_bus/__init__.py
golem/event_bus/base.py
golem/event_bus/in_memory/__init__.py
golem/event_bus/in_memory/event_bus.py
golem/exceptions.py
golem/managers/__init__.py
golem/managers/activity/__init__.py
golem/managers/activity/defaults.py
golem/managers/activity/mixins.py
golem/managers/activity/pool.py
golem/managers/activity/single_use.py
golem/managers/agreement/__init__.py
golem/managers/agreement/default.py
golem/managers/base.py
golem/managers/demand/__init__.py
golem/managers/demand/aggregating.py
golem/managers/demand/refreshing.py
golem/managers/demand/single_use.py
golem/managers/mixins.py
golem/managers/network/__init__.py
golem/managers/network/single.py
golem/managers/payment/__init__.py
golem/managers/payment/default.py
golem/managers/proposal/__init__.py
golem/managers/proposal/default.py
golem/managers/proposal/plugins/__init__.py
golem/managers/proposal/plugins/blacklist.py
golem/managers/proposal/plugins/buffer.py
golem/managers/proposal/plugins/linear_coeffs.py
golem/managers/proposal/plugins/negotiating/__init__.py
golem/managers/proposal/plugins/negotiating/mid_agreement_payments.py
golem/managers/proposal/plugins/negotiating/negotiating_plugin.py
golem/managers/proposal/plugins/negotiating/payment_platform.py
golem/managers/proposal/plugins/reject_costs_exceeds.py
golem/managers/proposal/plugins/scoring/__init__.py
golem/managers/proposal/plugins/scoring/map.py
golem/managers/proposal/plugins/scoring/mixins.py
golem/managers/proposal/plugins/scoring/pricings.py
golem/managers/proposal/plugins/scoring/property_value_lerp.py
golem/managers/proposal/plugins/scoring/random.py
golem/managers/proposal/plugins/scoring/scoring_buffer.py
golem/managers/proposal/plugins/whitelist.py
golem/managers/work/__init__.py
golem/managers/work/concurrent.py
golem/managers/work/mixins.py
golem/managers/work/plugins.py
golem/managers/work/sequential.py
golem_core-0.7.8.dist-info/LICENSE
golem_core-0.7.8.dist-info/METADATA
golem_core-0.7.8.dist-info/WHEEL
golem_core-0.7.8.dist-info/RECORD
